LICENSE
MANIFEST.in
README.rst
requirements.txt
setup.py
s3_uploader/__init__.py
s3_uploader/main.py
s3_uploader.egg-info/PKG-INFO
s3_uploader.egg-info/SOURCES.txt
s3_uploader.egg-info/dependency_links.txt
s3_uploader.egg-info/entry_points.txt
s3_uploader.egg-info/requires.txt
s3_uploader.egg-info/top_level.txt
s3_uploader/exceptions/__init__.py
s3_uploader/exceptions/validation_exception.py
s3_uploader/uploader/__init__.py
s3_uploader/uploader/handle_resource.py
s3_uploader/uploader/upload.py
s3_uploader/uploader/validation.py
s3_uploader/utils/__init__.py
s3_uploader/utils/exception_handler.py
s3_uploader/utils/s3_utils.py
s3_uploader/utils/utils.py
tests/uploader/__init__.py
tests/uploader/test_validation.py
tests/utils/__init__.py
tests/utils/test_utils.py