Metadata-Version: 1.0
Name: s3-uploader
Version: 0.0.6
Summary: Command line tool for uploading resources to S3
Home-page: https://github.com/onfido/s3-uploader/
Author: Onfido
Author-email: UNKNOWN
License: MIT
Keywords: python,s3,aws,upload,binaries,resources,boto3,uploader
Platform: UNKNOWN
